valmi_connector_lib/__init__.py
valmi_connector_lib/common/__init__.py
valmi_connector_lib/common/constants.py
valmi_connector_lib/common/logs.py
valmi_connector_lib/common/metrics.py
valmi_connector_lib/common/run_time_args.py
valmi_connector_lib/common/samples.py
valmi_connector_lib/destination_wrapper/__init__.py
valmi_connector_lib/destination_wrapper/destination_container_wrapper.py
valmi_connector_lib/destination_wrapper/destination_write_wrapper.py
valmi_connector_lib/destination_wrapper/engine.py
valmi_connector_lib/destination_wrapper/proc_stdout_event_handlers.py
valmi_connector_lib/destination_wrapper/proc_stdout_handler.py
valmi_connector_lib/destination_wrapper/read_handlers.py
valmi_connector_lib/source_wrapper/__init__.py
valmi_connector_lib/source_wrapper/source_container_wrapper.py
valmi_connector_lib/valmi_destination/__init__.py
valmi_connector_lib/valmi_destination/valmi_destination.py
valmi_connector_lib/valmi_protocol/__init__.py
valmi_connector_lib/valmi_protocol/valmi_event.py
valmi_connector_lib/valmi_protocol/valmi_protocol.py
valmi_connector_lib-0.1.192.dist-info/METADATA
valmi_connector_lib-0.1.192.dist-info/WHEEL
valmi_connector_lib-0.1.192.dist-info/RECORD
