Metadata-Version: 2.1
Name: valmi-connector-lib
Version: 0.1.192
Summary: 
Author: Rajashekar Varkala
Author-email: raj@valmi.io
Requires-Python: >=3.9,<4.0
Classifier: Programming Language :: Python :: 3
Classifier: Programming Language :: Python :: 3.9
Classifier: Programming Language :: Python :: 3.10
Classifier: Programming Language :: Python :: 3.11
Classifier: Programming Language :: Python :: 3.12
Requires-Dist: pydantic (>=1.9.2,<2.0.0)
Requires-Dist: requests (>=2.30.0,<3.0.0)
Requires-Dist: valmi-airbyte-cdk (>=0.30.3,<0.31.0)
